gnippy/__init__.py
gnippy/config.py
gnippy/errors.py
gnippy/powertrackclient.py
gnippy/rules.py
gnippy-0.7.0.dist-info/LICENSE.txt
gnippy-0.7.0.dist-info/METADATA
gnippy-0.7.0.dist-info/WHEEL
gnippy-0.7.0.dist-info/top_level.txt
gnippy-0.7.0.dist-info/RECORD
