Metadata-Version: 2.1
Name: gnippy
Version: 0.7.0
Summary: Python library for GNIP.
Home-page: http://pypi.python.org/pypi/gnippy/
Author: Abhinav Ajgaonkar
Author-email: abhinav316@gmail.com
License: Copyright 2012-2016 Abhinav Ajgaonkar and the Gnippy contributors.
Requires-Dist: requests (<3.0.0,>=2.8.1)
Requires-Dist: six (>=1.10.0)
